[{"id":"d7a3eb69-9212-4b9d-98d7-ac5bdfe105da","name":" EXA FM: Popmusik på engelska och spanska","country":"AX","tags":["moi merino","åland islands"],"homepage":"https://exafm.com/","favicon":"https://cdn-profiles.tunein.com/s90984/images/logog.png","language":"spanish","votes":72,"clickcount":4,"codec":"AAC+","bitrate":48,"streams":[{"url":"https://27063.live.streamtheworld.com:443/XHPSFMAAC.aac","format":"aac+","bitrate":48,"reliability":1}],"state":"Veracruz, México","languagecodes":"es"},{"id":"a940d9eb-b262-4d06-917b-457a03e0e140","name":"Ålands Radio","country":"AX","tags":[],"homepage":"https://alandsradio.ax/","favicon":"https://alandsradio.ax/sites/default/files/favicon_artv.ico","language":"swedish","votes":77,"clickcount":3,"codec":"OGG","bitrate":0,"streams":[{"url":"https://stream.alandsradio.ax/stream.ogg","format":"ogg","bitrate":0,"reliability":1}],"state":"","languagecodes":"sv"}]
