[{"id":"713c836b-96a1-484c-a8b2-df3d588388c1","name":"Narodni Radio - Sarajevo","country":"BA","tags":["bih","bosna","narodni","narodni radio","sarajevo"],"homepage":"http://narodni.ba/","favicon":"https://narodni.ba/wp-content/uploads/2020/08/cropped-narodni-logo-512-180x180.png","language":"bosnian","votes":3981,"clickcount":38,"codec":"AAC+","bitrate":128,"streams":[{"url":"http://server1.tnt.ba:8010/","format":"aac+","bitrate":128,"reliability":1}],"state":"","languagecodes":"bs"},{"id":"ab6e9c24-d163-446e-a4a9-ead8579c89f8","name":"BALKAN HiT RADIO - SARAJEVO","country":"BA","tags":["folk","mix","narodna"],"homepage":"https://balkanhitradio.com/","favicon":"https://i.ibb.co/HgJg79L/logobalkan.png","language":"","votes":1602,"clickcount":25,"codec":"MP3","bitrate":128,"streams":[{"url":"https://cast2.asurahosting.com/proxy/balkanhi/stream","format":"mp3","bitrate":128,"reliability":1}],"state":"Sarajevo","languagecodes":""},{"id":"dae342d7-42ae-43bb-90ff-43450af4523f","name":"Kalman Radio","country":"BA","tags":["bih","bosna","kalman","narodni","sarajevo"],"homepage":"https://kalmanradio.ba/","favicon":"","language":"bosnian","votes":251,"clickcount":18,"codec":"MP3","bitrate":128,"streams":[{"url":"http://188.40.62.20:8004/stream","format":"mp3","bitrate":128,"reliability":1}],"state":"","languagecodes":"bs"},{"id":"815be578-d795-438d-822c-09fa91c78286","name":"\tRadio Tešanj 92.2MHz","country":"BA","tags":[],"homepage":"https://www.radiotesanj.ba/","favicon":"https://www.radiotesanj.ba/assets/site/assets/images/logo-white-mobile.png","language":"bosnian","votes":98,"clickcount":18,"codec":"MP3","bitrate":128,"streams":[{"url":"http://radio.daj.ba:8082/stream","format":"mp3","bitrate":128,"reliability":1}],"state":"","languagecodes":"bs"},{"id":"961fb8a9-0601-11e8-ae97-52543be04c81","name":"Big Radio 1 Banja Luka","country":"BA","tags":["pop","rock"],"homepage":"http://www.bigradiobl.com/","favicon":"http://www.bigradiobl.com/favicon.png","language":"serbian","votes":1421,"clickcount":15,"codec":"AAC+","bitrate":36,"streams":[{"url":"http://big1.bigportal.ba:8100/big1","format":"aac+","bitrate":36,"reliability":1}],"state":"","languagecodes":"sr"},{"id":"9c421149-7dd8-11e8-b68b-52543be04c81","name":"Big2","country":"BA","tags":["banja luka","republica srbska"],"homepage":"http://bigportal.ba/","favicon":"","language":"serbian","votes":4293,"clickcount":14,"codec":"AAC+","bitrate":36,"streams":[{"url":"http://big2.bigportal.ba:8100/big2","format":"aac+","bitrate":36,"reliability":1}],"state":"","languagecodes":"sr"},{"id":"5cab177d-49de-492b-af93-f4467fd25690","name":"Radio Miljacka","country":"BA","tags":["folk music"],"homepage":"https://www.radiomiljacka.ba/","favicon":"https://www.phonostar.de/images/auto_created/Radio_Miljacka184x184.png","language":"bosnian","votes":123,"clickcount":13,"codec":"MP3","bitrate":128,"streams":[{"url":"https://radiomiljacka-bhcloud.radioca.st/stream.mp3","format":"mp3","bitrate":128,"reliability":1}],"state":"Sarajevo","languagecodes":"bs"},{"id":"e17c4dc1-42ff-4466-9925-bab2408cecac","name":"Velkaton","country":"BA","tags":["folk"],"homepage":"http://www.velkaton.ba/","favicon":"","language":"bosnian","votes":731,"clickcount":12,"codec":"MP3","bitrate":128,"streams":[{"url":"http://188.40.62.20:8044/;stream.mp3?_=1","format":"mp3","bitrate":128,"reliability":1}],"state":" Una-Sana Canton","languagecodes":"bs"},{"id":"961d91a2-0601-11e8-ae97-52543be04c81","name":"Radio BN","country":"BA","tags":["folk"],"homepage":"http://www.rtvbn.com/","favicon":"https://rtvbn.com/storage/settings/res_1720552469_favicon.png","language":"bosnian","votes":3125,"clickcount":12,"codec":"MP3","bitrate":192,"streams":[{"url":"https://stream.radiobn.net/;.mp3","format":"mp3","bitrate":192,"reliability":1}],"state":"","languagecodes":"bs"},{"id":"15c563f9-4f74-11ea-b877-52543be04c81","name":"Big Radio 4 Domaćica","country":"BA","tags":[],"homepage":"http://bigportal.ba/","favicon":"https://bigportal.ba/wp-content/uploads/2023/09/cropped-big-1-180x180.png","language":"serbian","votes":952,"clickcount":12,"codec":"AAC+","bitrate":32,"streams":[{"url":"http://domacica.bigportal.ba:8100/domacica","format":"aac+","bitrate":32,"reliability":1}],"state":"Republic of Srpska","languagecodes":"sr"},{"id":"cf682d35-486d-4378-9f24-d371e23d1112","name":"Radio Rujnica Zavidovici","country":"BA","tags":[],"homepage":"http://www.radiorujnica.net/","favicon":"","language":"bosnian","votes":175,"clickcount":11,"codec":"MP3","bitrate":128,"streams":[{"url":"https://r.name.ba:7115/stream","format":"mp3","bitrate":128,"reliability":1}],"state":"","languagecodes":"bs"},{"id":"ce2b6ae2-7650-461a-8324-a36a39631bd7","name":"Balkan Hip-Hop Radio","country":"BA","tags":["balkan","banja luka","bosnia","cool","ex-yu","hip hop","hip-hop","hiphop"],"homepage":"https://balkanhiphopradio.com/","favicon":"","language":"bosnian,croatian,macedonian,montenegrin,serbian,slovenian","votes":188,"clickcount":11,"codec":"MP3","bitrate":96,"streams":[{"url":"http://centova.dukahosting.com:2022/stream","format":"mp3","bitrate":96,"reliability":1}],"state":"Republika Srpska","languagecodes":"bs,hr,mk,sl,sr"},{"id":"08a07369-bda2-463c-94c2-36fae4e4c2ac","name":"Radio Cazin","country":"BA","tags":[],"homepage":"https://crt.ba/","favicon":"https://crt.ba/wp-content/uploads/2021/11/crtLogo.png","language":"bosnian","votes":77,"clickcount":10,"codec":"MP3","bitrate":128,"streams":[{"url":"http://195.222.33.217:8095/","format":"mp3","bitrate":128,"reliability":1}],"state":"","languagecodes":"bs"},{"id":"9fcccba7-d1a2-4066-a337-0a1bbb788b11","name":"Srce Krajine","country":"BA","tags":[],"homepage":"https://srce-krajine.com/","favicon":"","language":"serbian","votes":1571,"clickcount":10,"codec":"MP3","bitrate":128,"streams":[{"url":"https://srv.mediastriming.com/8330/stream","format":"mp3","bitrate":128,"reliability":1}],"state":"","languagecodes":"sr"},{"id":"6eff3da1-3b39-4b6b-b904-8c7a019c2812","name":"Radio Kalesijski Ba ","country":"BA","tags":["folk music"],"homepage":"https://kalesijski.ba/","favicon":"https://kalesijski.ba/radio","language":"bosnian","votes":11,"clickcount":9,"codec":"MP3","bitrate":128,"streams":[{"url":"https://stream1.srvnetplus.com:18102/","format":"mp3","bitrate":128,"reliability":1}],"state":"FBiH","languagecodes":"bs"},{"id":"86ea5de0-4701-4901-bb00-f329507b404b","name":"Radio Džungla Doboj 2","country":"BA","tags":[],"homepage":"https://dzungla.net/","favicon":"https://dzungla.net/radio-live/wp-content/uploads/2019/11/dzungla-radio-wh-m.png","language":"bosnian","votes":174,"clickcount":9,"codec":"MP3","bitrate":128,"streams":[{"url":"http://cast2.name.ba:9054/","format":"mp3","bitrate":128,"reliability":1}],"state":"","languagecodes":"bs"},{"id":"99db57d2-fae1-4cd9-a9cd-a361274123be","name":"BH Radio 1","country":"BA","tags":["music","news","talk"],"homepage":"https://bhrt.ba/bhr1-uzivo/","favicon":"https://bhrt.ba/favicon.ico","language":"bosnian","votes":1220,"clickcount":9,"codec":"UNKNOWN","bitrate":128,"streams":[{"url":"https://webtvstream.bhtelecom.ba/bh_radio1.m3u8","format":"unknown","bitrate":128,"reliability":1}],"state":"","languagecodes":"bs"},{"id":"d2abcac6-76ce-11e8-83fa-52543be04c81","name":"Radio Posavina Zagreb","country":"BA","tags":["folk"],"homepage":"https://radioposavina.com/","favicon":"","language":"","votes":1636,"clickcount":8,"codec":"MP3","bitrate":128,"streams":[{"url":"http://cmr-hosting.com:8500/;stream.mp3","format":"mp3","bitrate":128,"reliability":1}],"state":"","languagecodes":""},{"id":"961228f3-0601-11e8-ae97-52543be04c81","name":"Radio Bir","country":"BA","tags":["religion","talk"],"homepage":"http://www.bir.ba/","favicon":"","language":"bosnian","votes":1144,"clickcount":7,"codec":"MP3","bitrate":128,"streams":[{"url":"http://188.40.62.20:8090/","format":"mp3","bitrate":128,"reliability":1}],"state":"Sarajevo","languagecodes":"bs"},{"id":"5b0e8a05-6059-4d21-91ae-e14a987fe59f","name":"Pop FM - Slusaj glasno!!!","country":"BA","tags":[],"homepage":"http://www.popfm.ba/","favicon":"http://www.popfm.ba/apple-icon-120x120.png","language":"","votes":102,"clickcount":7,"codec":"MP3","bitrate":128,"streams":[{"url":"http://188.40.62.20:8032/;stream.nsv","format":"mp3","bitrate":128,"reliability":1}],"state":"","languagecodes":""},{"id":"f0b70616-202d-4fe5-8ad3-486291d17b09","name":"Thrash Metal","country":"BA","tags":[],"homepage":"https://www.edin.ba/","favicon":"","language":"","votes":566,"clickcount":7,"codec":"AAC+","bitrate":320,"streams":[{"url":"http://79.120.77.11:8000/thrashmetal","format":"aac+","bitrate":320,"reliability":1}],"state":"","languagecodes":""},{"id":"c64a7302-08db-4ad6-9b85-e379ee65ea77","name":" Radio DAŠ","country":"BA","tags":["folk"],"homepage":"http://www.radiodas.net/","favicon":"","language":"serbian","votes":394,"clickcount":7,"codec":"MP3","bitrate":128,"streams":[{"url":"http://158.69.119.6:8095/;&type=mp3","format":"mp3","bitrate":128,"reliability":1}],"state":"Republic of Srpska","languagecodes":"sr"},{"id":"23a0d2d4-724e-4ce4-9c3a-7e96d4cbe792","name":"Pakao Radio","country":"BA","tags":["rock"],"homepage":"https://www.pakaoradio.net/","favicon":"https://www.pakaoradio.net/img/bigthumb.jpg","language":"","votes":301,"clickcount":7,"codec":"MP3","bitrate":128,"streams":[{"url":"https://securestream.pakaoradio.net/live","format":"mp3","bitrate":128,"reliability":1}],"state":"","languagecodes":""},{"id":"090ac8e3-e46a-4e45-ba7f-6cc578e62137","name":"Kalman Radio","country":"BA","tags":[],"homepage":"https://kalmanradio.ba/","favicon":"http://kalmanradio.ba/wp-content/uploads/2018/02/web-logo.png","language":"","votes":49,"clickcount":7,"codec":"MP3","bitrate":0,"streams":[{"url":"https://ssl.surfmusic.de/s.php?s=http://188.40.62.20:8004/stream?1707015516","format":"mp3","bitrate":0,"reliability":1}],"state":"","languagecodes":""},{"id":"256ae503-ec6f-4d0d-b2f2-2d7e59d83932","name":"Radio Avlija","country":"BA","tags":[],"homepage":"https://radioavlija.com/","favicon":"","language":"bosnian","votes":74,"clickcount":6,"codec":"MP3","bitrate":128,"streams":[{"url":"http://51.255.127.128:8900/;","format":"mp3","bitrate":128,"reliability":1}],"state":"","languagecodes":"bs"},{"id":"18a26d7f-d0ff-489b-b326-fcd7e15ec0c4","name":"Radio Bihać","country":"BA","tags":[],"homepage":"https://www.radiobihac.com/","favicon":"https://www.radiobihac.com/images/logo/logo.png","language":"bosnian","votes":73,"clickcount":6,"codec":"MP3","bitrate":128,"streams":[{"url":"http://radiobihaclive.radioca.st:8249/stream","format":"mp3","bitrate":128,"reliability":1}],"state":"","languagecodes":"bs"},{"id":"8774cb71-f2ac-4e37-a02a-e15da844eff2","name":"Koprivljanski radio","country":"BA","tags":[],"homepage":"https://www.koprivljanskiradio.com/","favicon":"https://www.koprivljanskiradio.com/images/13654287_1017881974927424_7392547567572622816_n.jpg","language":"bosnian","votes":66,"clickcount":6,"codec":"AAC+","bitrate":128,"streams":[{"url":"http://cast2.name.ba:8101/","format":"aac+","bitrate":128,"reliability":1}],"state":"","languagecodes":"bs"},{"id":"8c6f96e4-d188-4578-8c85-a5b85012453f","name":"Radio Mango","country":"BA","tags":[],"homepage":"https://radiomango.eu/","favicon":"https://radiomango.eu/wp-content/uploads/2020/11/cropped-MANGO-PROZIRNA.png","language":"","votes":42,"clickcount":6,"codec":"MP3","bitrate":128,"streams":[{"url":"http://158.69.119.6:8780/stream","format":"mp3","bitrate":128,"reliability":1}],"state":"","languagecodes":""},{"id":"7b1b984d-4ee2-42cb-b7ad-143d8837bea4","name":"avaz radio","country":"BA","tags":[],"homepage":"https://www.radioavaz.net/","favicon":"https://www.radioavaz.net/photos/muzicki%20radio%20avaz.png","language":"bosnian","votes":89,"clickcount":6,"codec":"MP3","bitrate":56,"streams":[{"url":"http://51.254.61.148:8222/","format":"mp3","bitrate":56,"reliability":1}],"state":"","languagecodes":"bs"},{"id":"60607676-de23-44cd-8e05-aecbce5332c9","name":" Radiopostaja Mir - Međugorje","country":"BA","tags":["catholic","christian","religious"],"homepage":"https://radio-medjugorje.com/","favicon":"","language":"croatian","votes":318,"clickcount":6,"codec":"MP3","bitrate":192,"streams":[{"url":"https://mirm.live/mir.mp3","format":"mp3","bitrate":192,"reliability":1}],"state":"Herzegovina-Neretva Canton","languagecodes":"hr"},{"id":"1304bee8-bacf-4eb0-9839-306d1473040f","name":"Radio Valentino","country":"BA","tags":[],"homepage":"https://valentinobh.com/","favicon":"","language":"bosnian","votes":163,"clickcount":5,"codec":"UNKNOWN","bitrate":128,"streams":[{"url":"https://webtvstream.bhtelecom.ba/radio_valentino.m3u8","format":"unknown","bitrate":128,"reliability":1}],"state":"","languagecodes":"bs"},{"id":"21c35895-22c1-11e9-a80b-52543be04c81","name":"BIG 3","country":"BA","tags":["banja luka","big 3","big radio"],"homepage":"http://www.bigradiobl.com/","favicon":"http://www.bigradiobl.com/favicon.png","language":"serbian","votes":693,"clickcount":5,"codec":"AAC+","bitrate":36,"streams":[{"url":"http://big3.bigportal.ba:8100/big3?1548653014620","format":"aac+","bitrate":36,"reliability":1}],"state":"Republic of Srpska","languagecodes":"sr"},{"id":"75090c56-754a-495f-8e8b-e6e6110776e0","name":"Radio Bosanski Brod","country":"BA","tags":[],"homepage":"http://www.brodradio.com/bb/","favicon":"","language":"bosnian","votes":76,"clickcount":5,"codec":"MP3","bitrate":128,"streams":[{"url":"https://zpilipov-geckohost.radioca.st/stream","format":"mp3","bitrate":128,"reliability":1}],"state":"","languagecodes":"bs"},{"id":"f7d6da8b-ec61-4121-89a2-6bfa77996eae","name":"BIG radio 1 Banja Luka","country":"BA","tags":["evergreen","pop","rock"],"homepage":"https://bigportal.ba/","favicon":"","language":"serbian","votes":87,"clickcount":5,"codec":"AAC+","bitrate":36,"streams":[{"url":"http://big1.bigportal.ba:8100/big1","format":"aac+","bitrate":36,"reliability":1}],"state":"Republika Srpska","languagecodes":"sr"},{"id":"541067fe-723f-4e66-834a-7e1589dffca5","name":"Radio Slobodna Evropa","country":"BA","tags":[],"homepage":"https://www.slobodnaevropa.org/","favicon":"https://www.slobodnaevropa.org/Content/responsive/RFE/sh-SH/img/logo.svg","language":"bosnian","votes":77,"clickcount":5,"codec":"MP3","bitrate":0,"streams":[{"url":"https://n04.radiojar.com/bugesa4nn3quv?rj-ttl=5&rj-tok=AAABmhWjz6oAITvALqYdq8ogbQ","format":"mp3","bitrate":0,"reliability":1}],"state":"","languagecodes":"bs"},{"id":"83472775-fa52-4632-899b-f0ebe2acf002","name":"RVK","country":"BA","tags":[],"homepage":"https://www.radiovkladusa.ba/","favicon":"https://www.radiovkladusa.ba/favicon.ico","language":"bosnian","votes":72,"clickcount":5,"codec":"MP3","bitrate":192,"streams":[{"url":"http://rvk2021.radioca.st:8206/stream","format":"mp3","bitrate":192,"reliability":1}],"state":"","languagecodes":"bs"},{"id":"fad97ae1-1719-4941-8097-395c49c8fd55","name":"Day Dee Eurodance Radio","country":"BA","tags":["dance","dj remix","eurodance"],"homepage":"https://daydeeeurodance.blogspot.com/","favicon":"","language":"english","votes":131,"clickcount":5,"codec":"MP3","bitrate":128,"streams":[{"url":"http://daydeeeurodance.stream.laut.fm/daydeeeurodance","format":"mp3","bitrate":128,"reliability":1}],"state":"","languagecodes":"en"},{"id":"5457b94d-4d12-42e5-88cb-bcef0cf74ea6","name":"Radio MIX, BiH","country":"BA","tags":["narodna - folk"],"homepage":"https://radio.radiomix.ba/","favicon":"https://radio.radiomix.ba/images/mix/logo.png","language":"bosnian","votes":22,"clickcount":5,"codec":"MP3","bitrate":192,"streams":[{"url":"https://stream.rsgmedia.ba/listen/radio_mix/radio.mp3","format":"mp3","bitrate":192,"reliability":1}],"state":"Sarajevo","languagecodes":"bs"},{"id":"55925da5-d41c-4bda-86d7-7366bb50020c","name":"Alpha 93.1 FM Riscado","country":"BA","tags":["dance","latin","pop","top 40"],"homepage":"http://www.vozdibonaire.com/","favicon":"null","language":"bonaire,spanish","votes":3,"clickcount":4,"codec":"MP3","bitrate":100,"streams":[{"url":"https://kadushi.westream.cloud/listen/alfafm/xstream","format":"mp3","bitrate":100,"reliability":1}],"state":"","languagecodes":"es"},{"id":"b958c002-0986-4806-8fb9-a3aac4a36859","name":"Radios 8 Sarajevo","country":"BA","tags":["music"],"homepage":"http://radio8.ba/","favicon":"","language":"bosnian","votes":352,"clickcount":4,"codec":"MP3","bitrate":128,"streams":[{"url":"https://radio8-bhcloud.radioca.st/1.mp3","format":"mp3","bitrate":128,"reliability":1}],"state":"KS","languagecodes":"bs"},{"id":"c0105a63-b8ae-475b-a153-a0406e139ef8","name":"Kontakt Radio","country":"BA","tags":[],"homepage":"https://mojkontakt.com/","favicon":"https://mojkontakt.com/wp-content/uploads/2022/11/Mediamodifier-Design-2.svg","language":"bosnian","votes":196,"clickcount":4,"codec":"MP3","bitrate":320,"streams":[{"url":"http://mojstream.eu:8114/kontaktradio","format":"mp3","bitrate":320,"reliability":1}],"state":"","languagecodes":"bs"},{"id":"bdbffffd-35b6-4c1f-b2e2-5cbf4ff91565","name":"Radio Bihać Folk","country":"BA","tags":[],"homepage":"https://www.radiobihac.com/","favicon":"","language":"bosnian","votes":101,"clickcount":4,"codec":"MP3","bitrate":128,"streams":[{"url":"http://5.9.13.39:8071/stream","format":"mp3","bitrate":128,"reliability":1}],"state":"","languagecodes":"bs"},{"id":"84694019-cfef-4e72-a5aa-dbdc8cedffbe","name":"Narodni Radio Tuzla","country":"BA","tags":[],"homepage":"https://narodni.ba/","favicon":"","language":"bosnian","votes":112,"clickcount":4,"codec":"AAC+","bitrate":128,"streams":[{"url":"http://server1.tnt.ba:9080/","format":"aac+","bitrate":128,"reliability":1}],"state":"","languagecodes":"bs"},{"id":"1b52f3a0-2920-4f17-a549-73c85713385f","name":"Kakanj, Radio Kakanj","country":"BA","tags":["folk","news","pop","talk"],"homepage":"https://radiokakanj.co.ba/","favicon":"https://cdn-profiles.tunein.com/s9967/images/logog.png","language":"bosnian","votes":136,"clickcount":4,"codec":"MP3","bitrate":96,"streams":[{"url":"http://cast2.name.ba:8067/","format":"mp3","bitrate":96,"reliability":1}],"state":"","languagecodes":"bs"},{"id":"961d9264-0601-11e8-ae97-52543be04c81","name":"Radio Brcko District","country":"BA","tags":["information","music"],"homepage":"http://www.radio-brcko.co.ba/","favicon":"","language":"bosnian","votes":562,"clickcount":4,"codec":"AAC+","bitrate":64,"streams":[{"url":"http://91.191.0.45:8000/","format":"aac+","bitrate":64,"reliability":1}],"state":"","languagecodes":"bs"},{"id":"6062cb3e-e27e-4505-bfdd-e6e7d756db7f","name":"RadioAktivan","country":"BA","tags":[],"homepage":"https://radioaktivan.ba/","favicon":"","language":"bosnian","votes":22,"clickcount":4,"codec":"MP3","bitrate":0,"streams":[{"url":"https://stream-177.zeno.fm/4qe0awx37wquv?zt=eyJhbGciOiJIUzI1NiJ9.eyJzdHJlYW0iOiI0cWUwYXd4Mzd3cXV2IiwiaG9zdCI6InN0cmVhbS0xNzcuemVuby5mbSIsInRtIjpmYWxzZSwicnR0bCI6NSwianRpIjoieHF0X2hIOWtTQ2VvanpNWjdISU05dyIsImlhdCI6MTc2MTMwMDE2MSwiZXhwIjoxNzYxMzAwMjIxfQ.2CwHZQgUrST8d6rEfewGlcXIXKVGzl7VKzYnKX0NtM4","format":"mp3","bitrate":0,"reliability":1}],"state":"","languagecodes":"bs"},{"id":"6445ddb7-c238-11e8-aaf2-52543be04c81","name":"HIT Radio Brčko","country":"BA","tags":["folk","pop"],"homepage":"http://www.rtvhit.com/","favicon":"","language":"bosnian","votes":883,"clickcount":3,"codec":"MP3","bitrate":320,"streams":[{"url":"http://51.254.61.148:8152/;autostart=1","format":"mp3","bitrate":320,"reliability":1}],"state":"","languagecodes":"bs"},{"id":"a318e302-cb18-45c7-8fda-305589f1780c","name":"RADIO M CAFE","country":"BA","tags":[],"homepage":"https://radiom.ba/en/homepage/","favicon":"https://radiom.ba/wp-content/uploads/2021/10/cafe-v3-768x768.jpg","language":"","votes":17,"clickcount":3,"codec":"MP3","bitrate":128,"streams":[{"url":"https://team-data.ba:9032//;","format":"mp3","bitrate":128,"reliability":1}],"state":"","languagecodes":""},{"id":"2a24228f-7084-4cc5-9f88-9e7449698a98","name":"Krajiški Radio Dubica","country":"BA","tags":[],"homepage":"https://www.krajiski-radio-dubica.com/","favicon":"","language":"","votes":762,"clickcount":3,"codec":"MP3","bitrate":128,"streams":[{"url":"https://stream1.srvnetplus.com:18039/","format":"mp3","bitrate":128,"reliability":1}],"state":"Republika Srpska","languagecodes":""},{"id":"66009a9b-64f6-4302-9b4e-e6bb9fdd9a37","name":"Radio ZENIT Zenica","country":"BA","tags":[],"homepage":"https://www.zenit.ba/","favicon":"https://www.zenit.ba/logo/zenit-header.png","language":"bosnian","votes":11,"clickcount":3,"codec":"MP3","bitrate":128,"streams":[{"url":"http://5.189.168.133:8020/1","format":"mp3","bitrate":128,"reliability":1}],"state":"","languagecodes":"bs"},{"id":"063f6556-7dd6-475a-b517-53c0a9b9b94b","name":"Radio Merak","country":"BA","tags":[],"homepage":"http://konjicanka.com/","favicon":"","language":"","votes":34,"clickcount":3,"codec":"MP3","bitrate":128,"streams":[{"url":"http://176.9.113.180:8084/stream","format":"mp3","bitrate":128,"reliability":1}],"state":"","languagecodes":""},{"id":"96299813-1489-4c76-b923-d5034aff3c81","name":"Radio Novi Grad 100MHz","country":"BA","tags":[],"homepage":"http://www.radionovigrad.com/","favicon":"","language":"","votes":89,"clickcount":3,"codec":"MP3","bitrate":128,"streams":[{"url":"http://s37.myradiostream.com:8120/;stream.mp3","format":"mp3","bitrate":128,"reliability":1}],"state":"Republika Srpska","languagecodes":""},{"id":"ef3eedbb-d60f-4f15-9f18-d875dc8f136e","name":"Radio Bosanska Krupa","country":"BA","tags":[],"homepage":"https://radiobk.ba/","favicon":"https://radiobk.ba/wp-content/uploads/2024/11/Radio1-300x112.png","language":"bosnian","votes":13,"clickcount":3,"codec":"UNKNOWN","bitrate":128,"streams":[{"url":"https://webtvstream.bhtelecom.ba/radio_bosanska_krupa.m3u8","format":"unknown","bitrate":128,"reliability":1}],"state":"","languagecodes":"bs"},{"id":"0365d198-551c-4764-a4bb-7e5d29a3cb6a","name":"Radio Kapija Los Angeles","country":"BA","tags":[],"homepage":"https://www.radiokapija.com/","favicon":"https://www.radiokapija.com/rkfiles/1380@2x.png","language":"bosnian","votes":7,"clickcount":3,"codec":"MP3","bitrate":192,"streams":[{"url":"https://s1.voscast.com:7471/stream","format":"mp3","bitrate":192,"reliability":1}],"state":"","languagecodes":"bs"},{"id":"0a61b972-aff2-47fa-91cd-edcc15900d33","name":"Radio Busovača","country":"BA","tags":["local news","music","public radio","talk show"],"homepage":"https://radio-busovaca.eu/","favicon":"","language":"bosnian,croatian","votes":152,"clickcount":3,"codec":"MP3","bitrate":128,"streams":[{"url":"https://ec2s.crolive.com.hr:1510/stream","format":"mp3","bitrate":128,"reliability":1}],"state":"","languagecodes":"bs,hr"},{"id":"c8b11c6d-89fd-419a-9d2e-8d4050590706","name":"Pop FM","country":"BA","tags":[],"homepage":"https://www.popfm.ba/","favicon":"https://popfm.ba/slike/popfm-logo.png","language":"bosnian","votes":46,"clickcount":3,"codec":"MP3","bitrate":128,"streams":[{"url":"http://188.40.62.20:8032/","format":"mp3","bitrate":128,"reliability":1}],"state":"","languagecodes":"bs"},{"id":"7ff36a8a-9ab0-4647-81c4-16d545ea858e","name":"RADIO ZENICA","country":"BA","tags":["classical"],"homepage":"","favicon":"","language":"","votes":131,"clickcount":3,"codec":"MP3","bitrate":128,"streams":[{"url":"http://stream.rtvze.ba:8000/stream","format":"mp3","bitrate":128,"reliability":1}],"state":"","languagecodes":""},{"id":"e0e4752b-1bf6-45ca-8f98-25d0804b5850","name":"Radio Bobar","country":"BA","tags":[],"homepage":"https://radiobobar.com/","favicon":"","language":"bosnian","votes":104,"clickcount":3,"codec":"MP3","bitrate":128,"streams":[{"url":"http://94.130.11.28:9010/","format":"mp3","bitrate":128,"reliability":1}],"state":"","languagecodes":"bs"},{"id":"845580a9-4dad-4f09-b194-ea7175263eb9","name":"Radio Srebrenik","country":"BA","tags":["folk"],"homepage":"","favicon":"","language":"","votes":370,"clickcount":3,"codec":"MP3","bitrate":256,"streams":[{"url":"http://live.radiosrebrenik.ba:7600/","format":"mp3","bitrate":256,"reliability":1}],"state":"","languagecodes":""},{"id":"96372853-0601-11e8-ae97-52543be04c81","name":"Radio Posušje","country":"BA","tags":["croatian","domaća","glazba","herceg-bosna","hercegovina","hrvatska","posusje","posušje"],"homepage":"http://www.radioposusje.ba/","favicon":"","language":"croatian","votes":217,"clickcount":3,"codec":"AAC+","bitrate":128,"streams":[{"url":"http://136.243.144.93:9994/","format":"aac+","bitrate":128,"reliability":1}],"state":"","languagecodes":"hr"},{"id":"8abede59-7462-4562-b9fb-ab809527e145","name":"Radio Vogošća","country":"BA","tags":[],"homepage":"https://www.rtvvogosca.ba/","favicon":"https://www.rtvvogosca.ba/logo6.png","language":"bosnian","votes":29,"clickcount":3,"codec":"UNKNOWN","bitrate":128,"streams":[{"url":"https://webtvstream.bhtelecom.ba/radio_vogosca.m3u8","format":"unknown","bitrate":128,"reliability":1}],"state":"","languagecodes":"bs"},{"id":"0115bf0e-6c79-4c9b-a811-ebc7b55d842e","name":"Slon Radio Tuzla","country":"BA","tags":["pop rock","tuzla"],"homepage":"https://rtvslon.ba/","favicon":"","language":"bosnian","votes":635,"clickcount":3,"codec":"MP3","bitrate":0,"streams":[{"url":"http://31.47.0.130:88/broadwavehigh.mp3?src=1;","format":"mp3","bitrate":0,"reliability":1}],"state":"","languagecodes":"bs"},{"id":"97610b24-1312-4038-a71b-d28d4478221d","name":"Radio Zenit - caffe","country":"BA","tags":[],"homepage":"https://www.zenit.ba/","favicon":"","language":"bosnian","votes":26,"clickcount":3,"codec":"MP3","bitrate":128,"streams":[{"url":"http://5.189.168.133:8020/stream/2/;","format":"mp3","bitrate":128,"reliability":1}],"state":"","languagecodes":"bs"},{"id":"c0c8ab11-ee88-47f1-b1d1-448c79185c55","name":"RadioMajevica.com","country":"BA","tags":["izvorna","narodna","zabavna"],"homepage":"https://www.radiomajevica.com/","favicon":"https://www.radiomajevica.com/favicon.ico","language":"bosnian","votes":4,"clickcount":3,"codec":"MP3","bitrate":64,"streams":[{"url":"https://live.radiomajevica.com:7520/live","format":"mp3","bitrate":64,"reliability":1}],"state":"","languagecodes":"bs"},{"id":"7e408d94-d99b-47d2-bbdd-c2936570de6b","name":"Radio Preporod Odzak 95,2","country":"BA","tags":[],"homepage":"https://www.radiopreporod.com/","favicon":"https://www.radiopreporod.com/mobile/index_htm_files/4889@2x.png","language":"bosnian","votes":36,"clickcount":3,"codec":"MP3","bitrate":192,"streams":[{"url":"http://s1.voscast.com:7986/;","format":"mp3","bitrate":192,"reliability":1}],"state":"","languagecodes":"bs"},{"id":"dae70c55-0666-45e4-ac43-fb8ff438afba","name":"Radio Gračanica","country":"BA","tags":[],"homepage":"https://radiogracanica.ba/","favicon":"","language":"bosnian","votes":15,"clickcount":3,"codec":"UNKNOWN","bitrate":128,"streams":[{"url":"https://webtvstream.bhtelecom.ba/radio_gracanica.m3u8","format":"unknown","bitrate":128,"reliability":1}],"state":"","languagecodes":"bs"},{"id":"2c88609a-c083-4ca2-8c8f-ed0adec35822","name":"RTV USK","country":"BA","tags":[],"homepage":"https://www.rtvusk.ba/","favicon":"https://www.rtvusk.ba/images/logo.png","language":"","votes":10,"clickcount":3,"codec":"MP3","bitrate":24,"streams":[{"url":"https://radiousk.radioca.st/stream","format":"mp3","bitrate":24,"reliability":1}],"state":"","languagecodes":""},{"id":"0bc9150d-c487-49c5-af59-7425284da4ff","name":"Radio \"Birač\" Milići","country":"BA","tags":["pop music"],"homepage":"http://radiobirac.ba/","favicon":"http://radiobirac.ba/radio-birac.ico","language":"serbian","votes":5,"clickcount":2,"codec":"MP3","bitrate":128,"streams":[{"url":"http://176.227.215.27:12932/;","format":"mp3","bitrate":128,"reliability":1}],"state":"Republika Srpska","languagecodes":"sr"},{"id":"56cd4a69-e582-431c-b0f8-c3ef1d32fa50","name":"Radio BA","country":"BA","tags":[],"homepage":"https://www.radioba.ba/","favicon":"https://www.radioba.ba/favicon.ico","language":"bosnian","votes":35,"clickcount":2,"codec":"UNKNOWN","bitrate":128,"streams":[{"url":"https://webtvstream.bhtelecom.ba/radio_ba.m3u8","format":"unknown","bitrate":128,"reliability":1}],"state":"","languagecodes":"bs"},{"id":"a3774158-97cf-4627-953b-06cd334028fd","name":"Narodni Radio Zenica","country":"BA","tags":[],"homepage":"https://narodni.ba/","favicon":"","language":"bosnian","votes":57,"clickcount":2,"codec":"AAC+","bitrate":128,"streams":[{"url":"http://server1.tnt.ba:9010/","format":"aac+","bitrate":128,"reliability":1}],"state":"","languagecodes":"bs"},{"id":"9420da6d-993d-40ae-ae23-b73e7d481bc6","name":"Pop FM Bosnia and Herzegovina","country":"BA","tags":[],"homepage":"http://www.popfm.ba/","favicon":"","language":"","votes":56,"clickcount":2,"codec":"MP3","bitrate":128,"streams":[{"url":"http://188.40.62.20:8032/;stream.nsv","format":"mp3","bitrate":128,"reliability":1}],"state":"","languagecodes":""},{"id":"ab2407e4-450c-4d94-9c94-ec891f9c88d9","name":"Radio Visoko","country":"BA","tags":["local music","local news","local radio"],"homepage":"http://radio.visoko-rtv.ba/","favicon":"https://www.visoko-rtv.ba/wp-content/uploads/2019/07/visocka_icon.png","language":"bosnian","votes":522,"clickcount":2,"codec":"MP3","bitrate":128,"streams":[{"url":"http://188.40.62.20:8080/","format":"mp3","bitrate":128,"reliability":1}],"state":"","languagecodes":"bs"},{"id":"07ee1980-f0fc-4c09-b694-e5cb09804867","name":"KUPRESKIRADIO","country":"BA","tags":["classical"],"homepage":"","favicon":"","language":"","votes":73,"clickcount":2,"codec":"AAC+","bitrate":64,"streams":[{"url":"https://ec2s.crolive.com.hr:1265/stream","format":"aac+","bitrate":64,"reliability":1}],"state":"","languagecodes":""},{"id":"23d83b85-8631-460b-aba8-c85ca83b50b4","name":"Radio Slon","country":"BA","tags":[],"homepage":"https://www.rtvslon.ba/","favicon":"","language":"","votes":469,"clickcount":2,"codec":"MP3","bitrate":0,"streams":[{"url":"http://31.47.0.130:88/broadwavehigh.mp3","format":"mp3","bitrate":0,"reliability":1}],"state":"TK","languagecodes":""},{"id":"7de34405-def3-4d3b-a8cf-66def205b71e","name":"Kalesijski Ba","country":"BA","tags":[],"homepage":"https://kalesijski.ba/","favicon":"https://kalesijski.ba/wp-content/uploads/2024/09/cropped-images-180x180.png","language":"","votes":317,"clickcount":2,"codec":"MP3","bitrate":128,"streams":[{"url":"http://5.9.95.57:8102/stream","format":"mp3","bitrate":128,"reliability":1}],"state":"","languagecodes":""},{"id":"79ac9cd5-2d2f-4016-a51a-160c4dad360a","name":"Radio Bosanski Petrovac","country":"BA","tags":[],"homepage":"https://bosanskipetrovac.gov.ba/","favicon":"","language":"bosnian","votes":53,"clickcount":2,"codec":"UNKNOWN","bitrate":128,"streams":[{"url":"https://webtvstream.bhtelecom.ba/radio_bosanski_petrovac.m3u8","format":"unknown","bitrate":128,"reliability":1}],"state":"","languagecodes":"bs"},{"id":"7e5cdea9-75b6-4798-92d2-70da0b88aa51","name":"Radio USK","country":"BA","tags":[],"homepage":"https://www.rtvusk.ba/tv/o-radiju","favicon":"","language":"bosn","votes":398,"clickcount":2,"codec":"MP3","bitrate":24,"streams":[{"url":"https://radiousk.radioca.st/stream","format":"mp3","bitrate":24,"reliability":1}],"state":"","languagecodes":""},{"id":"961d8f65-0601-11e8-ae97-52543be04c81","name":"Nes Radio","country":"BA","tags":["information","music"],"homepage":"http://www.nesradio.com/","favicon":"","language":"bosnian","votes":1952,"clickcount":2,"codec":"MP3","bitrate":192,"streams":[{"url":"http://188.40.62.20:8070/;","format":"mp3","bitrate":192,"reliability":1}],"state":"","languagecodes":"bs"},{"id":"536e2b7c-7415-4021-a31d-183e283a2558","name":"Radio Ključ","country":"BA","tags":[],"homepage":"https://www.media-kljuc.ba/","favicon":"","language":"bosnian","votes":38,"clickcount":2,"codec":"MP3","bitrate":112,"streams":[{"url":"http://195.222.33.217:8093/;","format":"mp3","bitrate":112,"reliability":1}],"state":"","languagecodes":"bs"},{"id":"f86a026c-259a-43c6-bd38-128963e0950e","name":"Radio Magic Milići","country":"BA","tags":["folk music"],"homepage":"https://www.magic.ba/","favicon":"","language":"serbian","votes":1,"clickcount":2,"codec":"MP3","bitrate":96,"streams":[{"url":"http://stream.iradio.pro:8034/;*.mp3","format":"mp3","bitrate":96,"reliability":1}],"state":"Republika Srpska","languagecodes":"sr"},{"id":"155b3bb7-0176-498f-9f50-b80b772cfa5d","name":"Abdulbasit Abdulsamad","country":"BA","tags":[],"homepage":"https://mp3islam.com/","favicon":"null","language":"arabic","votes":2,"clickcount":2,"codec":"MP3","bitrate":192,"streams":[{"url":"https://radio.mp3islam.com/listen/abdulbasit/radio.mp3","format":"mp3","bitrate":192,"reliability":1}],"state":"","languagecodes":"ar"},{"id":"719d8893-1c53-4040-b5bc-a00345a0898e","name":"novii","country":"BA","tags":["classical"],"homepage":"","favicon":"","language":"","votes":384,"clickcount":2,"codec":"MP3","bitrate":128,"streams":[{"url":"http://s37.myradiostream.com:8120/","format":"mp3","bitrate":128,"reliability":1}],"state":"","languagecodes":""},{"id":"b813c53b-c1d0-4daf-9071-66e5eead0c85","name":"Radio Breza","country":"BA","tags":["bosna"],"homepage":"https://www.radiobreza.com.ba/","favicon":"https://www.phonostar.de/images/auto_created/Radio_Breza2124x124.png","language":"bosnian","votes":9,"clickcount":2,"codec":"MP3","bitrate":128,"streams":[{"url":"https://sonicpanel.vmakerhost.com/8192/stream","format":"mp3","bitrate":128,"reliability":1}],"state":"","languagecodes":"bs"},{"id":"529200e4-4945-492a-9f37-b57f65174bcd","name":"Radio HIT FM","country":"BA","tags":[],"homepage":"https://hitfm.ba/","favicon":"https://hitfm.ba/wp-content/uploads/2022/08/Logo-hitfmradio.png","language":"bosnian","votes":66,"clickcount":2,"codec":"UNKNOWN","bitrate":128,"streams":[{"url":"https://webtvstream.bhtelecom.ba/radio_hit_fm.m3u8","format":"unknown","bitrate":128,"reliability":1}],"state":"","languagecodes":"bs"},{"id":"ed2fa1ad-0153-408e-8489-35b4e3e94dd9","name":"RADIO KISS KISELJAK","country":"BA","tags":["classical"],"homepage":"","favicon":"","language":"","votes":100,"clickcount":2,"codec":"MP3","bitrate":140,"streams":[{"url":"http://stream.kissfm.ba:8010/live","format":"mp3","bitrate":140,"reliability":1}],"state":"","languagecodes":""},{"id":"2a8b101d-e5e1-46c5-a4b5-54320b25e5b8","name":"Islamski Radio","country":"BA","tags":[],"homepage":"http://www.islamski-radio.com/index.php/sr/","favicon":"","language":"bosnian","votes":86,"clickcount":2,"codec":"MP3","bitrate":96,"streams":[{"url":"http://eu3.fastcast4u.com:5762/stream","format":"mp3","bitrate":96,"reliability":1}],"state":"","languagecodes":"bs"},{"id":"58265cf7-b41d-4308-b0f9-25c6d8c367fa","name":"Radio Olovo","country":"BA","tags":[],"homepage":"https://radio.olovo.ba/","favicon":"https://radio.olovo.ba/storage/2020/04/logo_radio_olovo@2x.png","language":"bosnian","votes":15,"clickcount":2,"codec":"AAC+","bitrate":64,"streams":[{"url":"http://sonicpanel.vmakerhost.com:8038/stream","format":"aac+","bitrate":64,"reliability":1}],"state":"","languagecodes":"bs"},{"id":"961d9331-0601-11e8-ae97-52543be04c81","name":"Radio Feral 100.4 Sarajevo","country":"BA","tags":["local"],"homepage":"http://www.uzivoradio.com/feral-kalesija.html","favicon":"http://www.uzivoradio.com/favicon.ico","language":"bosnian","votes":815,"clickcount":2,"codec":"MP3","bitrate":96,"streams":[{"url":"http://185.50.56.3/;stream.nsv","format":"mp3","bitrate":96,"reliability":1}],"state":"","languagecodes":"bs"},{"id":"e62438ca-ab93-4cc7-8f58-277126e6dbed","name":"Moj Radio","country":"BA","tags":[],"homepage":"http://www.mojradio.ba/","favicon":"","language":"bosnian","votes":67,"clickcount":2,"codec":"UNKNOWN","bitrate":128,"streams":[{"url":"https://webtvstream.bhtelecom.ba/moj_radio.m3u8","format":"unknown","bitrate":128,"reliability":1}],"state":"","languagecodes":"bs"},{"id":"a852ebc9-ae89-43f4-b1bc-e346e801ac45","name":"Radio Gradačac","country":"BA","tags":[],"homepage":"https://radiogradacac.ba/","favicon":"","language":"bosnian","votes":26,"clickcount":2,"codec":"UNKNOWN","bitrate":128,"streams":[{"url":"https://webtvstream.bhtelecom.ba/radio_gradacac.m3u8","format":"unknown","bitrate":128,"reliability":1}],"state":"","languagecodes":"bs"},{"id":"058490c3-5a29-11e9-a622-52543be04c81","name":"RADIO MARIA BOSNIA","country":"BA","tags":["catholic","religion"],"homepage":"https://www.radiomarija.ba/","favicon":"","language":"bosnian","votes":880,"clickcount":2,"codec":"MP3","bitrate":64,"streams":[{"url":"http://dreamsiteradiocp.com:8034/stream","format":"mp3","bitrate":64,"reliability":1}],"state":"","languagecodes":"bs"},{"id":"48c3aef1-25f7-417b-ba15-7b1e38362032","name":"Radio USK","country":"BA","tags":[],"homepage":"https://www.rtvusk.ba/","favicon":"","language":"bosnian","votes":43,"clickcount":2,"codec":"UNKNOWN","bitrate":128,"streams":[{"url":"https://webtvstream.bhtelecom.ba/radio_usk.m3u8","format":"unknown","bitrate":128,"reliability":1}],"state":"","languagecodes":"bs"},{"id":"d28f2bbc-64c2-4f0d-b65c-d9e7dff80ac2","name":"Radio Bugojno","country":"BA","tags":[],"homepage":"https://rtvbugojno.ba/","favicon":"https://rtvbugojno.ba/favicon.ico","language":"bosnian","votes":15,"clickcount":2,"codec":"MP3","bitrate":128,"streams":[{"url":"https://s3.free-shoutcast.com/stream/18156","format":"mp3","bitrate":128,"reliability":1}],"state":"","languagecodes":"bs"},{"id":"b3a1daea-b4e0-4d47-b16a-81c3b468a92f","name":"Radio M","country":"BA","tags":[],"homepage":"https://radiom.ba/","favicon":"https://radiom.ba/wp-content/uploads/2021/06/Radio-M-rotacija.gif","language":"bosnian","votes":476,"clickcount":2,"codec":"MP3","bitrate":128,"streams":[{"url":"http://www.team-data.ba:8030/stream/","format":"mp3","bitrate":128,"reliability":1}],"state":"","languagecodes":"bs"},{"id":"6d9bcd3f-075d-4f61-b3bf-2db0bb01e3fc","name":"Radio Džungla Doboj 3","country":"BA","tags":[],"homepage":"https://dzungla.net/","favicon":"https://dzungla.net/radio-live/wp-content/uploads/2019/11/dzungla-radio-wh-m.png","language":"bosnian","votes":48,"clickcount":2,"codec":"MP3","bitrate":128,"streams":[{"url":"http://cast2.name.ba:8006/","format":"mp3","bitrate":128,"reliability":1}],"state":"","languagecodes":"bs"},{"id":"33f25513-5120-4a20-9f1c-dbaa26e0b9cc","name":"Radio Kameleon","country":"BA","tags":[],"homepage":"https://radiokameleon.ba/","favicon":"","language":"bosnian","votes":117,"clickcount":2,"codec":"UNKNOWN","bitrate":128,"streams":[{"url":"https://webtvstream.bhtelecom.ba/radio_kameleon.m3u8","format":"unknown","bitrate":128,"reliability":1}],"state":"","languagecodes":"bs"},{"id":"1557aeb4-37b3-47af-b4d8-9a442297134d","name":"Radio Prača","country":"BA","tags":[],"homepage":"https://www.radiopraca.ba/","favicon":"","language":"bosnian","votes":9,"clickcount":2,"codec":"UNKNOWN","bitrate":128,"streams":[{"url":"https://webtvstream.bhtelecom.ba/radio_praca.m3u8","format":"unknown","bitrate":128,"reliability":1}],"state":"","languagecodes":"bs"},{"id":"b3abd1ea-ded6-41d9-9a19-ecf420bdae31","name":"Radio Bihać Caffe","country":"BA","tags":[],"homepage":"https://www.radiobihac.com/","favicon":"","language":"bosnian","votes":28,"clickcount":2,"codec":"MP3","bitrate":128,"streams":[{"url":"http://5.9.13.39:8075/stream","format":"mp3","bitrate":128,"reliability":1}],"state":"","languagecodes":"bs"},{"id":"253708f4-de52-410d-b3c4-50f9b99c1fe1","name":"Radio - Livno","country":"BA","tags":[],"homepage":"https://radiolivno.ba/","favicon":"","language":"bosnian","votes":25,"clickcount":2,"codec":"MP3","bitrate":128,"streams":[{"url":"http://cast2.name.ba:8127/stream/","format":"mp3","bitrate":128,"reliability":1}],"state":"","languagecodes":"bs"},{"id":"45ae78d9-f03e-4eac-a17a-6416491edad9","name":"Radio Veseli Bosanac","country":"BA","tags":[],"homepage":"https://veselibosanac.com/","favicon":"","language":"bosnian","votes":65,"clickcount":2,"codec":"MP3","bitrate":128,"streams":[{"url":"http://opportunity.shoutca.st:8038/","format":"mp3","bitrate":128,"reliability":1}],"state":"","languagecodes":"bs"},{"id":"0356e497-ffb7-11e9-bbf2-52543be04c81","name":"Kupreški Radio","country":"BA","tags":["nebeski radio"],"homepage":"https://www.kupreskiradio.com/","favicon":"","language":"bosnian,croatian","votes":203,"clickcount":2,"codec":"MP3","bitrate":192,"streams":[{"url":"http://178.209.2.100:10000/live.mp3","format":"mp3","bitrate":192,"reliability":1}],"state":"Kanton 10","languagecodes":"bs,hr"},{"id":"2f1f3d95-d30f-428e-a15d-6ec1f982b486","name":"ROBOT HIT RADIO","country":"BA","tags":[],"homepage":"http://robothitradio.com/","favicon":"http://robothitradio.com/pause.png","language":"","votes":13,"clickcount":2,"codec":"MP3","bitrate":128,"streams":[{"url":"https://slusaj.off.ba/radio/8000/robot","format":"mp3","bitrate":128,"reliability":1}],"state":"","languagecodes":""},{"id":"2f0491fa-02b3-4ed9-83ab-4f12a5e89b0a","name":"Radio Trebinje","country":"BA","tags":[],"homepage":"https://radiotrebinje.com/?lang=lat","favicon":"https://radiotrebinje.com/assets/rt/images/logo.jpg","language":"bosnian","votes":12,"clickcount":2,"codec":"AAC+","bitrate":48,"streams":[{"url":"https://radio.dukahosting.com:7002/","format":"aac+","bitrate":48,"reliability":1}],"state":"","languagecodes":"bs"},{"id":"a55ff23b-a273-4025-8fea-ee59f851e4e2","name":"Radio Orašje","country":"BA","tags":[],"homepage":"https://www.radioorasje.com/o-nama/","favicon":"","language":"bosnian","votes":27,"clickcount":2,"codec":"MP3","bitrate":128,"streams":[{"url":"http://188.40.62.20:8024/","format":"mp3","bitrate":128,"reliability":1}],"state":"","languagecodes":"bs"},{"id":"097b746e-cc96-4432-99f2-9d33b0a5137c","name":"Federalni Radio","country":"BA","tags":[],"homepage":"http://www.rtvfbih.ba/","favicon":"","language":"bosnian","votes":195,"clickcount":1,"codec":"UNKNOWN","bitrate":128,"streams":[{"url":"https://webtvstream.bhtelecom.ba/radio_fbih.m3u8","format":"unknown","bitrate":128,"reliability":1}],"state":"","languagecodes":"bs"},{"id":"62f1cf05-5c5e-49ab-9137-a83350f65273","name":"Radio Grude","country":"BA","tags":["misc"],"homepage":"","favicon":"","language":"","votes":111,"clickcount":1,"codec":"MP3","bitrate":192,"streams":[{"url":"http://radio.pa-hosting.de:1040/","format":"mp3","bitrate":192,"reliability":1}],"state":"","languagecodes":""},{"id":"306f08fb-7eed-45ad-9ff3-8dac5a05e5ab","name":"Radio Laktasi","country":"BA","tags":[],"homepage":"https://laktasiturizam.org/","favicon":"","language":"","votes":9,"clickcount":1,"codec":"MP3","bitrate":320,"streams":[{"url":"https://radio.laktasiturizam.org/live","format":"mp3","bitrate":320,"reliability":1}],"state":"Republika Srpska","languagecodes":""},{"id":"a199193d-22f4-47b6-a117-1197f7a6b38c","name":"Radio Lukavac","country":"BA","tags":[],"homepage":"https://rtvlukavac.ba/","favicon":"","language":"bosnian","votes":104,"clickcount":1,"codec":"MP3","bitrate":192,"streams":[{"url":"http://195.222.33.217:8022/","format":"mp3","bitrate":192,"reliability":1}],"state":"","languagecodes":"bs"},{"id":"0474ae26-b53f-4ee8-b812-882d6cbb2a7c","name":"Radio Magic","country":"BA","tags":[],"homepage":"http://www.magic.ba/","favicon":"","language":"bosnian","votes":65,"clickcount":1,"codec":"MP3","bitrate":96,"streams":[{"url":"http://stream.iradio.pro:8034/radiomagic","format":"mp3","bitrate":96,"reliability":1}],"state":"","languagecodes":"bs"},{"id":"7b6756aa-1fe0-485b-a897-ffa3e25b5b86","name":"RADIO VITEZ","country":"BA","tags":["classical"],"homepage":"https://www.radiovitez.ba/","favicon":"","language":"","votes":55,"clickcount":1,"codec":"MP3","bitrate":128,"streams":[{"url":"https://radio.iti.hr/listen/radio_vitez/radio.mp3","format":"mp3","bitrate":128,"reliability":1}],"state":"","languagecodes":""},{"id":"b0094504-b26c-49ab-8ae1-c0477dd4b661","name":"Radio 7 Tuzla","country":"BA","tags":[],"homepage":"https://rtv7.ba/","favicon":"https://rtv7.ba/favicon.ico","language":"bosnian","votes":69,"clickcount":1,"codec":"UNKNOWN","bitrate":128,"streams":[{"url":"https://webtvstream.bhtelecom.ba/radio_7_tuzla.m3u8","format":"unknown","bitrate":128,"reliability":1}],"state":"","languagecodes":"bs"},{"id":"e656bc8c-d013-46d4-ac39-14bd0c295d52","name":"Radio TK","country":"BA","tags":[],"homepage":"https://rtvtk.ba/","favicon":"","language":"bosnian","votes":64,"clickcount":1,"codec":"UNKNOWN","bitrate":128,"streams":[{"url":"https://webtvstream.bhtelecom.ba/radio_tk.m3u8","format":"unknown","bitrate":128,"reliability":1}],"state":"","languagecodes":"bs"},{"id":"5e64847a-8514-4c52-9dd4-61bd3a3e320f","name":"Radio Miljacka","country":"BA","tags":[],"homepage":"https://www.radiomiljacka.ba/","favicon":"","language":"","votes":13,"clickcount":1,"codec":"MP3","bitrate":128,"streams":[{"url":"https://radiomiljacka-bhcloud.radioca.st/stream.mp3","format":"mp3","bitrate":128,"reliability":1}],"state":"","languagecodes":""},{"id":"f0fbc23b-cc64-48a3-9e5b-0e130ce663c9","name":"Radio 8 Sarajevo","country":"BA","tags":[],"homepage":"https://www.radio8.ba/","favicon":"","language":"bosnian","votes":40,"clickcount":1,"codec":"MP3","bitrate":128,"streams":[{"url":"https://radio8-bhcloud.radioca.st/1.mp3","format":"mp3","bitrate":128,"reliability":1}],"state":"","languagecodes":"bs"},{"id":"649b6727-96e8-42fb-9b7e-bfab6593c8f4","name":"﻿﻿Radio Osvit","country":"BA","tags":["bosnia","serbian music"],"homepage":"https://www.radioosvit.com/","favicon":"","language":"serbian","votes":7,"clickcount":1,"codec":"MP3","bitrate":128,"streams":[{"url":"https://radio.dukahosting.com/8020/stream","format":"mp3","bitrate":128,"reliability":1}],"state":"Republika Srpska","languagecodes":"sr"},{"id":"852d9181-8264-40b4-b8f5-8c3567c50e16","name":"Radio ASK Ilidža","country":"BA","tags":[],"homepage":"http://www.ask.ba/","favicon":"","language":"bosnian","votes":19,"clickcount":1,"codec":"UNKNOWN","bitrate":128,"streams":[{"url":"https://webtvstream.bhtelecom.ba/radio_ask.m3u8","format":"unknown","bitrate":128,"reliability":1}],"state":"","languagecodes":"bs"},{"id":"11c5f24d-fad5-4ceb-9579-d5aa8cd1efe6","name":"RADIO ZENIT","country":"BA","tags":["classical"],"homepage":"","favicon":"","language":"","votes":51,"clickcount":1,"codec":"MP3","bitrate":128,"streams":[{"url":"http://5.189.168.133:8020/1","format":"mp3","bitrate":128,"reliability":1}],"state":"","languagecodes":""},{"id":"2cdb8f50-415a-4912-aa6b-99e2ec21ba99","name":"Radio Ljubuški","country":"BA","tags":[],"homepage":"https://radioljubuski.ba/","favicon":"https://encrypted-tbn0.gstatic.com/images?q=tbn:ANd9GcTaI3lhMhQrBrc3EkwkguvmYxa0NMChBnaS2zdLOhy91w&s","language":"bosnian","votes":11,"clickcount":1,"codec":"MP3","bitrate":96,"streams":[{"url":"https://s8.iqstreaming.com:8044/stream","format":"mp3","bitrate":96,"reliability":1}],"state":"","languagecodes":"bs"},{"id":"5484cd9f-57c7-4d42-a3e9-9e6a026fe4bb","name":"Radio Konjic","country":"BA","tags":[],"homepage":"https://radiokonjic.ba/","favicon":"","language":"bosnian","votes":20,"clickcount":1,"codec":"UNKNOWN","bitrate":128,"streams":[{"url":"https://webtvstream.bhtelecom.ba/radio_konjic.m3u8","format":"unknown","bitrate":128,"reliability":1}],"state":"","languagecodes":"bs"},{"id":"94e75dd3-ec35-41df-888a-068cc1bc78e5","name":"Radio Donji Vakuf","country":"BA","tags":[],"homepage":"https://radiodonjivakuf.com.ba/","favicon":"","language":"bosnian","votes":30,"clickcount":1,"codec":"MP3","bitrate":128,"streams":[{"url":"http://5.9.71.122:8134/;stream.mp3","format":"mp3","bitrate":128,"reliability":1}],"state":"","languagecodes":"bs"},{"id":"08963e11-87c0-4a7b-8c05-4eb2321f29ef","name":"Antena Radio, Jelah Tešanj","country":"BA","tags":[],"homepage":"http://www.antena-radio.ba/","favicon":"","language":"bosnian","votes":423,"clickcount":1,"codec":"MP3","bitrate":128,"streams":[{"url":"https://radio.tnt.ba/radio/8020/live?1616060583","format":"mp3","bitrate":128,"reliability":1}],"state":"","languagecodes":"bs"},{"id":"c39d1a7e-038e-432c-b0b6-7bcfc047538d","name":"Radio Čapljina","country":"BA","tags":["various"],"homepage":"https://radio-capljina.com/","favicon":"https://rpc.visici.com/wp-content/uploads/2023/01/radio-capljina-box2-bijela.png","language":"bosnian","votes":5,"clickcount":1,"codec":"MP3","bitrate":96,"streams":[{"url":"http://s8.iqstreaming.com:8016/stream","format":"mp3","bitrate":96,"reliability":1}],"state":"Ruđera Boškovića 4, Čapljina","languagecodes":"bs"},{"id":"2548bc19-6f98-401a-ae25-fe38bdb1a7c5","name":"Radio Trebinje","country":"BA","tags":[],"homepage":"https://radiotrebinje.com/","favicon":"https://radiotrebinje.com/assets/rt/images/logo.jpg","language":"","votes":6,"clickcount":1,"codec":"AAC+","bitrate":48,"streams":[{"url":"https://radio.dukahosting.com:7002/;","format":"aac+","bitrate":48,"reliability":1}],"state":"","languagecodes":""},{"id":"56b21d29-9b9a-4a1e-a452-6cd816776079","name":"Imperia Radio","country":"BA","tags":[],"homepage":"https://imperia.tv/","favicon":"https://upload.wikimedia.org/wikipedia/bs/5/58/Imperia_logo.jpg?20200315174653","language":"bosnian","votes":12,"clickcount":1,"codec":"UNKNOWN","bitrate":128,"streams":[{"url":"https://webtvstream.bhtelecom.ba/imperia_radio.m3u8","format":"unknown","bitrate":128,"reliability":1}],"state":"","languagecodes":"bs"},{"id":"52249342-ea22-47f0-82ce-e118cad324f2","name":"Radio RTRS","country":"BA","tags":[],"homepage":"https://lat.rtrs.tv/","favicon":"https://lat.rtrs.tv/_bmp/logo-127x37.png","language":"bosnian","votes":73,"clickcount":1,"codec":"UNKNOWN","bitrate":128,"streams":[{"url":"https://webtvstream.bhtelecom.ba/radio_rtrs.m3u8","format":"unknown","bitrate":128,"reliability":1}],"state":"","languagecodes":"bs"},{"id":"c6233833-5674-4277-b346-a73ad0aa1841","name":"Radio Feral Kalesija","country":"BA","tags":[],"homepage":"https://www.radio-feral.ba/","favicon":"https://www.radio-feral.ba/wp-content/uploads/2022/10/FERAL-LOGO-STRANICA-WEB-1.jpg","language":"bosnian","votes":17,"clickcount":1,"codec":"UNKNOWN","bitrate":128,"streams":[{"url":"https://webtvstream.bhtelecom.ba/radio_feral_kalesija.m3u8","format":"unknown","bitrate":128,"reliability":1}],"state":"","languagecodes":"bs"},{"id":"57b2875b-29e0-4745-a225-2122e8a752e9","name":"Novi Radio Bihać","country":"BA","tags":[],"homepage":"http://www.noviradiobihac.com/","favicon":"","language":"bosnian","votes":30,"clickcount":1,"codec":"UNKNOWN","bitrate":128,"streams":[{"url":"https://webtvstream.bhtelecom.ba/novi_radio_bihac.m3u8","format":"unknown","bitrate":128,"reliability":1}],"state":"","languagecodes":"bs"},{"id":"cd358fa7-6aea-446e-95f9-7a3af24910e0","name":"Radio Čapljina","country":"BA","tags":[],"homepage":"https://radio-capljina.com/","favicon":"https://radio-capljina.com/wp-content/uploads/2023/01/radio-capljina-box2-bijela.png","language":"bosnian","votes":41,"clickcount":1,"codec":"MP3","bitrate":96,"streams":[{"url":"http://s8.iqstreaming.com:8016/","format":"mp3","bitrate":96,"reliability":1}],"state":"","languagecodes":"bs"},{"id":"c0c055c6-210a-4e59-aa6b-295436f89347","name":"Radio Goražde","country":"BA","tags":[],"homepage":"https://rtvbpk.ba/","favicon":"https://rtvbpk.ba/wp-content/uploads/2017/12/radio-gz.jpg","language":"bosnian","votes":16,"clickcount":1,"codec":"UNKNOWN","bitrate":128,"streams":[{"url":"https://webtvstream.bhtelecom.ba/radio_gorazde.m3u8","format":"unknown","bitrate":128,"reliability":1}],"state":"","languagecodes":"bs"},{"id":"af183f50-a1ed-402b-a35a-5cf3f166bbd3","name":"Radio Usora","country":"BA","tags":[],"homepage":"https://www.radio-usora-dijaspora.com/","favicon":"","language":"bosnian","votes":28,"clickcount":1,"codec":"UNKNOWN","bitrate":128,"streams":[{"url":"https://webtvstream.bhtelecom.ba/radio_usora.m3u8","format":"unknown","bitrate":128,"reliability":1}],"state":"","languagecodes":"bs"},{"id":"be352707-1663-483c-92f0-48e7123a764c","name":"Radio Usora","country":"BA","tags":[],"homepage":"https://www.radiousora.info/","favicon":"","language":"bosnian","votes":6,"clickcount":0,"codec":"UNKNOWN","bitrate":128,"streams":[{"url":"https://webtvstream.bhtelecom.ba/radio_usora.m3u8","format":"unknown","bitrate":128,"reliability":1}],"state":"","languagecodes":"bs"},{"id":"961d9543-0601-11e8-ae97-52543be04c81","name":"Radio Marija","country":"BA","tags":["catholic"],"homepage":"http://www.radiomarija.ba/","favicon":"http://www.radiomarija.ba/templates/t3_bs3_blank/favicon.ico","language":"bosnian","votes":314,"clickcount":0,"codec":"MP3","bitrate":64,"streams":[{"url":"http://dreamsiteradiocp.com:8034/","format":"mp3","bitrate":64,"reliability":1}],"state":"","languagecodes":"bs"}]
