[{"id":"d6fe71f3-899b-4b72-8e88-fee0d3a2e76f","name":"L.A. Mega 98.1 FM","country":"PA","tags":[],"homepage":"https://lamegapanama.com/","favicon":"https://lamegapanama.com/wp-content/uploads/2024/08/logo-png369-x-150-px.png","language":"","votes":45,"clickcount":12,"codec":"AAC","bitrate":112,"streams":[{"url":"https://www.streaming507.net:8152/stream","format":"aac","bitrate":112,"reliability":1}],"state":"","languagecodes":""},{"id":"963165f8-dc1c-4b6f-bdcd-cd833715b7a3","name":"TropiQ","country":"PA","tags":[],"homepage":"https://tropiq.com/","favicon":"https://www.tropiq.com/wp-content/uploads/2018/06/Logo-Tropi-Q.png","language":"","votes":48,"clickcount":8,"codec":"AAC+","bitrate":320,"streams":[{"url":"https://www.streaming507.net:8140/stream","format":"aac+","bitrate":320,"reliability":1}],"state":"","languagecodes":""},{"id":"7560d23e-8605-4032-a0df-a8fe37242a7b","name":"Estéreo Azul 100.9 FM","country":"PA","tags":["entretenimiento","latino","merengue","salsa","tropical"],"homepage":"https://www.estereoazul.com/","favicon":"https://www.estereoazul.com/wp-content/uploads/2019/03/logo-azul-1.png","language":"spanish","votes":180,"clickcount":7,"codec":"AAC+","bitrate":48,"streams":[{"url":"https://14103.live.streamtheworld.com:443/ESTEREOAZULAAC.aac","format":"aac+","bitrate":48,"reliability":1}],"state":"","languagecodes":"es"},{"id":"2f940f39-39a2-494f-9eb1-b20776f585ac","name":"Los 40 Panamá","country":"PA","tags":[],"homepage":"https://los40.com.pa/","favicon":"https://los40pa00.epimg.net/los40/iconos/v2.x/v1.0/logos/logo_40_principales_menu.png","language":"","votes":34,"clickcount":5,"codec":"MP3","bitrate":48,"streams":[{"url":"https://16603.live.streamtheworld.com/LOS40_PAN_SC?dist=onlineradiobox","format":"mp3","bitrate":48,"reliability":1}],"state":"","languagecodes":""},{"id":"7dab00b3-72f6-49ba-bb7c-de55a8097afd","name":"LA BUENA RADIO PANAMA","country":"PA","tags":[],"homepage":"https://www.labuenaradiopanama.com/","favicon":"https://image.jimcdn.com/app/cms/image/transf/none/path/s2063d334a8dd968c/image/i6c8eec74aa7b1080/version/1631334098/image.png","language":"","votes":51,"clickcount":5,"codec":"AAC","bitrate":64,"streams":[{"url":"https://s3.voscast.com:8607/live","format":"aac","bitrate":64,"reliability":1}],"state":"","languagecodes":""},{"id":"7b5f6f3a-74fc-4f01-b165-b48c83f3e797","name":"Flow 92.7 FM","country":"PA","tags":["hits","latino","mix","reggaeton","urbano"],"homepage":"https://x.com/flow927fm","favicon":"https://statics-v3.streema.com/static/img/radios/profile_background_default_380.abf7abe7e86a.jpg","language":"spanish","votes":103,"clickcount":4,"codec":"AAC+","bitrate":128,"streams":[{"url":"http://streaming507.net:9980/stream","format":"aac+","bitrate":128,"reliability":1}],"state":"","languagecodes":"es"},{"id":"960b3af3-0601-11e8-ae97-52543be04c81","name":"AM Original 1180 Veraguas","country":"PA","tags":["folkloric"],"homepage":"http://www.amoriginal.net/","favicon":"https://amoriginal.net/wp-content/uploads/2024/03/cropped-logo_am_original_v2_512x512-180x180.png","language":"spanish","votes":654,"clickcount":4,"codec":"MP3","bitrate":96,"streams":[{"url":"http://rosetta.shoutca.st:9264/stream","format":"mp3","bitrate":96,"reliability":1}],"state":"Veraguas","languagecodes":"es"},{"id":"962dbde6-0601-11e8-ae97-52543be04c81","name":"Los 40 Principales Panamá","country":"PA","tags":["latin pop","top 40"],"homepage":"http://www.los40.com.pa/","favicon":"","language":"spanish","votes":1310,"clickcount":4,"codec":"MP3","bitrate":48,"streams":[{"url":"http://25083.live.streamtheworld.com:3690/LOS40_PAN_SC","format":"mp3","bitrate":48,"reliability":1}],"state":"Panama City","languagecodes":"es"},{"id":"2372baf4-797e-4ba6-b124-dad255b8967b","name":"Antena 8 100.1 FM","country":"PA","tags":["2000s","2010s","90s","comercială","hits","musica","radio hablada"],"homepage":"https://www.antena8.com/","favicon":"https://www.antena8.com/wp-content/uploads/2019/04/logo-antena-peque.png","language":"spanish","votes":124,"clickcount":4,"codec":"AAC+","bitrate":48,"streams":[{"url":"https://14983.live.streamtheworld.com:443/ANT8AAC.aac","format":"aac+","bitrate":48,"reliability":1}],"state":"","languagecodes":"es"},{"id":"65ece5f4-e9f5-4c0d-a8e2-f59b9c9d5a8b","name":"CHT FM 107.7","country":"PA","tags":["entretenimiento","musica","tropical","vallenato"],"homepage":"https://www.cht1077.com/","favicon":"https://www.cht1077.com/images/bg.jpg ","language":"spanish","votes":66,"clickcount":4,"codec":"MP3","bitrate":128,"streams":[{"url":"https://radios.host-pa.com:8046/;","format":"mp3","bitrate":128,"reliability":1}],"state":"","languagecodes":"es"},{"id":"d2b2716c-e431-4421-9cb2-c32b16de8d41","name":"Radio Disney Panamá FM 101.3","country":"PA","tags":[],"homepage":"https://pa.radiodisney.com/","favicon":"https://i.imgur.com/O5Q2O0I.png","language":"","votes":31,"clickcount":3,"codec":"MP3","bitrate":128,"streams":[{"url":"https://ic.streann.com/disneypanama","format":"mp3","bitrate":128,"reliability":1}],"state":"","languagecodes":""},{"id":"f570d89b-d8d3-4016-a1d2-42248689be8d","name":"Omega Stereo","country":"PA","tags":["classic rock","talk"],"homepage":"https://www.omegastereo.com/","favicon":"https://pbs.twimg.com/profile_images/1246331679/Twiter_400x400.jpg","language":"","votes":35,"clickcount":3,"codec":"AAC","bitrate":96,"streams":[{"url":"https://www.streaming507.net:8048/stream","format":"aac","bitrate":96,"reliability":1}],"state":"","languagecodes":"es-419"},{"id":"960968be-0601-11e8-ae97-52543be04c81","name":"Radio Disney Panamá","country":"PA","tags":["teen pop"],"homepage":"http://radiodisney.disneylatino.com/panama","favicon":"","language":"spanish","votes":1101,"clickcount":3,"codec":"MP3","bitrate":128,"streams":[{"url":"http://ic.streann.com:8000/disneypanama","format":"mp3","bitrate":128,"reliability":1}],"state":"Panama City","languagecodes":"es"},{"id":"1e586ac9-e78b-4522-b7ad-5cbf483257d1","name":"Fabulosa Estéreo 100.5 FM","country":"PA","tags":["bachata","dj","latino","mix","reggae","reggaeton","salsa","urbano"],"homepage":"https://fabulosaestereo.com/","favicon":"","language":"spanish","votes":145,"clickcount":3,"codec":"AAC+","bitrate":320,"streams":[{"url":"https://www.streaming507.net:8130/stream","format":"aac+","bitrate":320,"reliability":1}],"state":"","languagecodes":"es"},{"id":"086c5754-5fdc-405b-9ed5-d2ec6dbc676c","name":"Infinity Panama","country":"PA","tags":[],"homepage":"https://infinitypanama.com/","favicon":"https://infinitypanama.com/assets/logo-qitDsT5a.png","language":"","votes":11,"clickcount":3,"codec":"MP3","bitrate":96,"streams":[{"url":"https://s2.mexside.net/8048/stream","format":"mp3","bitrate":96,"reliability":1}],"state":"","languagecodes":""},{"id":"0b59023f-7eaf-4f86-89ae-2d2e6e25a424","name":"RPC Radio","country":"PA","tags":[],"homepage":"https://rpcradio.com/","favicon":"https://www.rpcradio.com/site/assets/files/others/2018/02/28/MEDGEN/1034/dummylogo.768x461.jpg","language":"","votes":40,"clickcount":3,"codec":"AAC","bitrate":66,"streams":[{"url":"https://s9.stweb.tv/thinkindot-fast-3/live/playlist.m3u8","format":"aac","bitrate":66,"reliability":1}],"state":"","languagecodes":""},{"id":"a3075574-5a91-11e9-a622-52543be04c81","name":"RADIO MARIA PANAMA","country":"PA","tags":["catholic","religion","talk"],"homepage":"http://www.radiomaria.pa/","favicon":"","language":"","votes":692,"clickcount":2,"codec":"MP3","bitrate":64,"streams":[{"url":"http://dreamsiteradiocp.com:8082/stream","format":"mp3","bitrate":64,"reliability":1}],"state":"","languagecodes":""},{"id":"cabdb540-aa7f-4bd8-bc4d-543063d6737e","name":"FM Corazón 102.5","country":"PA","tags":["amor","baladas en español","music","musica romantica"],"homepage":"https://fmcorazonellenguajedelamor.com/","favicon":"https://fmcorazonellenguajedelamor.com/wp-content/uploads/2024/04/fmcorazon-150x150.jpeg ","language":"spanish","votes":64,"clickcount":2,"codec":"MP3","bitrate":128,"streams":[{"url":"https://sp4.colombiatelecom.com.co/8006/stream","format":"mp3","bitrate":128,"reliability":1}],"state":"","languagecodes":"es"},{"id":"6ae8d373-5ab7-46bf-9dfa-98be08292f76","name":"Radio Mia - Los Santos","country":"PA","tags":[],"homepage":"https://radiomia920.com/","favicon":"https://i.imgur.com/5rr1CgI.jpeg","language":"","votes":8,"clickcount":2,"codec":"AAC+","bitrate":32,"streams":[{"url":"https://sonic.globalstream.pro/8040/stream","format":"aac+","bitrate":32,"reliability":1}],"state":"","languagecodes":""},{"id":"7a757629-89b4-4569-9912-ba7142f2ed01","name":"Forever Virtual Radio","country":"PA","tags":[],"homepage":"https://forevervirtual.net/","favicon":"https://forevervirtual.net/wp-content/uploads/2021/10/ForeverVirtualRadio_s.jpg","language":"","votes":20,"clickcount":2,"codec":"MP3","bitrate":128,"streams":[{"url":"https://s5.voscast.com:9885/stream?1742605500366","format":"mp3","bitrate":128,"reliability":1}],"state":"","languagecodes":""},{"id":"36395653-8cd9-40e2-bd4b-1ce9c3e6d50b","name":"LA TIPIK","country":"PA","tags":[],"homepage":"https://x.com/latipikradio","favicon":"https://pbs.twimg.com/profile_images/1233402500671250437/lEGH0-Yd_400x400.jpg","language":"","votes":17,"clickcount":2,"codec":"MP3","bitrate":256,"streams":[{"url":"https://stream.mixesurbanospty.com:8090/tipik.mp3","format":"mp3","bitrate":256,"reliability":1}],"state":"","languagecodes":""},{"id":"37562f27-e290-4065-b5ae-a70c43eb2737","name":"RADIO MARIA PANAMA","country":"PA","tags":[],"homepage":"https://radiomaria.pa/","favicon":"https://radiomaria.pa/wp-content/themes/radiomaria/img/logo-chiaro.png","language":"","votes":10,"clickcount":2,"codec":"AAC+","bitrate":32,"streams":[{"url":"https://dreamsiteradiocp2.com/proxy/rmpanama2?mp=/stream","format":"aac+","bitrate":32,"reliability":1}],"state":"","languagecodes":""},{"id":"23749ae2-31cb-4121-9145-96fe81e66f31","name":"Original Stereo 90.7 FM","country":"PA","tags":["cumbia","musica latina","reggaetón","salsa"],"homepage":"https://originalstereo.net/","favicon":"","language":"spanish","votes":335,"clickcount":2,"codec":"MP3","bitrate":192,"streams":[{"url":"http://rosetta.shoutca.st:8931/;","format":"mp3","bitrate":192,"reliability":1}],"state":"","languagecodes":"es"},{"id":"4817a306-7501-47db-b73f-2d3ea7e394ae","name":"YXY","country":"PA","tags":[],"homepage":"https://grupojapradiotv.com/","favicon":"https://grupojapradiotv.com/wp-content/themes/yootheme/cache/47/yxy-4721fd1e.webp","language":"","votes":5,"clickcount":2,"codec":"MP3","bitrate":128,"streams":[{"url":"https://sp4.colombiatelecom.com.co:8006/stream","format":"mp3","bitrate":128,"reliability":1}],"state":"","languagecodes":""},{"id":"99ebebde-0bac-4d39-84f5-f6035b6a9514","name":"República Retro","country":"PA","tags":[],"homepage":"https://republicaretropty.wixsite.com/website","favicon":"https://static.wixstatic.com/media/92485e_ff2b2e45b8554dfbae2298ed5abbbbd9~mv2.png/v1/fill/w_100,h_100,al_c,q_85,usm_0.66_1.00_0.01,enc_avif,quality_auto/92485e_ff2b2e45b8554dfbae2298ed5abbbbd9~mv2.png","language":"","votes":34,"clickcount":2,"codec":"MP3","bitrate":0,"streams":[{"url":"https://stream-175.zeno.fm/k3ekxp11xrquv?zt=eyJhbGciOiJIUzI1NiJ9.eyJzdHJlYW0iOiJrM2VreHAxMXhycXV2IiwiaG9zdCI6InN0cmVhbS0xNzUuemVuby5mbSIsInRtIjpmYWxzZSwicnR0bCI6NSwianRpIjoiaEpia0thSHZRek9NMUtYZENXNkdyZyIsImlhdCI6MTc2MTM3MTY4MSwiZXhwIjoxNzYxMzcxNzQxfQ.4RnN3OPRK5vq4xYI3m6Asxygc-hjDf5KZ2AztUvkMwg","format":"mp3","bitrate":0,"reliability":1}],"state":"","languagecodes":""},{"id":"c7372749-49a0-4514-8f24-406d2fe66699","name":"Telemetro Radio","country":"PA","tags":[],"homepage":"https://www.telemetro.com/radio","favicon":"https://static2.mytuner.mobi/media/tvos_radios/103/telemetro-radio.d78fb02c.png","language":"","votes":26,"clickcount":2,"codec":"AAC","bitrate":98,"streams":[{"url":"https://s9.stweb.tv/thinkindot-fast-1/live/playlist.m3u8","format":"aac","bitrate":98,"reliability":1}],"state":"","languagecodes":""},{"id":"5b3a4e81-6363-44d9-ae84-7ac26f5732bc","name":"XTREME MUSIC RADIO","country":"PA","tags":[],"homepage":"https://www.xtrememusicradio.com/","favicon":"https://static.wixstatic.com/media/1728fa_8ff77ffd99004cda9ca904cbe9dc25a5~mv2.png/v1/fill/w_233,h_72,al_c,q_85,usm_0.66_1.00_0.01,enc_auto/XTREME%20negro.png","language":"","votes":62,"clickcount":2,"codec":"MP3","bitrate":320,"streams":[{"url":"https://radios.sonicp.com/8020/stream","format":"mp3","bitrate":320,"reliability":1}],"state":"","languagecodes":""},{"id":"25975ffe-136a-4c96-b25a-2225cdaa52ad","name":"Original Stereo 90.7 FM","country":"PA","tags":[],"homepage":"https://www.originalstereo.net/","favicon":"https://www.originalstereo.net/wp-content/uploads/2023/07/LOGO_ORIGINAL_STEREO.png","language":"","votes":8,"clickcount":1,"codec":"MP3","bitrate":192,"streams":[{"url":"https://original.radioca.st/;","format":"mp3","bitrate":192,"reliability":1}],"state":"","languagecodes":""},{"id":"caca1367-6c8d-455f-9ed5-59ca82a9b925","name":"FM99","country":"PA","tags":[],"homepage":"https://www.fm99t-vs.com/","favicon":"https://www.fm99t-vs.com/wp-content/uploads/2024/12/logowebblanco.png","language":"","votes":19,"clickcount":1,"codec":"MP3","bitrate":320,"streams":[{"url":"https://a8.asurahosting.com:6580/radio.mp3","format":"mp3","bitrate":320,"reliability":1}],"state":"","languagecodes":""},{"id":"0685eddf-858f-4034-99e5-40d959688900","name":"Stereo Vida Panama","country":"PA","tags":["bible","cristiana","evangelio","religious"],"homepage":"https://stereovida.org/","favicon":"https://stereovida.org/mt-content/uploads/2023/05/stereo-vida.jpg","language":"spanish","votes":41,"clickcount":1,"codec":"MP3","bitrate":0,"streams":[{"url":"https://stream-160.zeno.fm/fz1rcfd1x1zuv?zt=eyJhbGciOiJIUzI1NiJ9.eyJzdHJlYW0iOiJmejFyY2ZkMXgxenV2IiwiaG9zdCI6InN0cmVhbS0xNjAuemVuby5mbSIsInRtIjpmYWxzZSwicnR0bCI6NSwianRpIjoiaDVDN2RuUERRM1M1NkFaQmRzZWQwdyIsImlhdCI6MTc2MTM1NTk2NSwiZXhwIjoxNzYxMzU2MDI1fQ.2SsCejQ21zSd5TTHxR83vydavwTBS10JHlvnNnaODJk","format":"mp3","bitrate":0,"reliability":1}],"state":"","languagecodes":"es"},{"id":"ed3bbacb-8945-4733-b641-c43e95146365","name":"TVN Radio","country":"PA","tags":[],"homepage":"https://www.tvn-2.com/","favicon":"https://cdn-profiles.tunein.com/s186597/images/logod.png","language":"","votes":38,"clickcount":1,"codec":"AAC","bitrate":213,"streams":[{"url":"https://us-b4-p-e-nq15-audio.cdn.mdstrm.com/live-audio/6495bd4ecd55fe08b4765b53/654a5c9f40fd924d7ba3cd41/playlist.m3u8?aid=6495bd4ecd55fe08b4765b53&dnt=true&uid=bd4OLrAP9gIxbw92y28cJBSUgVhCxWFY&sid=XbHbf3SdW8OPynroe95JSyz2nfB3iN5C&pid=coEcFUo064cTG0feq0zr1KKM5touhYMQ&ref=tvn-especiales-editorial-comercial.s3.us-east-2.amazonaws.com&es=us-b4-p-e-nq15-audio.cdn.mdstrm.com&ote=1761479647279&ot=RLmGUIiQGOrfD_fK8KTIyw&proto=https&pz=us&cP=128000","format":"aac","bitrate":213,"reliability":1}],"state":"","languagecodes":""},{"id":"37f0a7ca-02db-4021-b1f9-689ac498194c","name":"Ultra Stereo 98.9 FM","country":"PA","tags":[],"homepage":"https://www.fmultrastereo.com/","favicon":"https://www.fmultrastereo.com/assets/images/logo-ultrastereo.png","language":"","votes":21,"clickcount":1,"codec":"AAC","bitrate":32,"streams":[{"url":"https://www.streaming507.net:8134/stream","format":"aac","bitrate":32,"reliability":1}],"state":"","languagecodes":""},{"id":"95dfbeef-7d88-4f4e-90db-e08466abf59c","name":"Rumba FM","country":"PA","tags":[],"homepage":"https://radioparallevar.com/","favicon":"","language":"","votes":110,"clickcount":1,"codec":"AAC+","bitrate":96,"streams":[{"url":"https://laradiossl.online:10355/;stream.nsv","format":"aac+","bitrate":96,"reliability":1}],"state":"","languagecodes":""},{"id":"43db44ab-92e1-4db8-8f38-8a4d9da2842c","name":"Brava Radio 507","country":"PA","tags":[],"homepage":"https://www.facebook.com/Brava-Radio-507-104005031609202/","favicon":"https://i.imgur.com/xAIF7eX.jpeg","language":"","votes":16,"clickcount":1,"codec":"AAC+","bitrate":64,"streams":[{"url":"https://laradiossl.online:10660/","format":"aac+","bitrate":64,"reliability":1}],"state":"","languagecodes":""},{"id":"323aca98-970c-4545-a667-b4abe656f7ee","name":"Festival 1540 AM","country":"PA","tags":["entrevistas","folklore","music","nacional","noticias","popular"],"homepage":"https://festival1540am.com/","favicon":"https://festival1540am.com/wp-content/uploads/2016/01/LOGO-NUEVO-transparente1.png","language":"spanish","votes":60,"clickcount":1,"codec":"AAC","bitrate":96,"streams":[{"url":"http://streaming507.net:8128/stream","format":"aac","bitrate":96,"reliability":1}],"state":"","languagecodes":"es"},{"id":"55379f7f-2692-473f-a83f-390a0aacfeb6","name":"Magic FM","country":"PA","tags":[],"homepage":"https://radioparallevar.com/magicfm/","favicon":"https://radioparallevar.com/wp-content/uploads/2020/08/magic_hd-e1695935759999.png","language":"","votes":14,"clickcount":1,"codec":"AAC+","bitrate":64,"streams":[{"url":"https://laradio.stream/proxy/magicfm/stream","format":"aac+","bitrate":64,"reliability":1}],"state":"","languagecodes":""},{"id":"b7b47392-a7f9-41db-a71c-0da58c81e6b7","name":"Exa FM","country":"PA","tags":["93.3 fm","entretenimiento","español","estación","exa","exa fm","fm","juvenil","la estación exacta","la estación naranja","moi merino","mvs","mvs noticias","mvs radio","música en español e inglés","música pop","ponte exa","pop","pop en español e inglés","pop music","pop rock","radio"],"homepage":"https://www.exafm.com/veracruz/","favicon":"https://www.exafm.com/favicon.ico","language":"spanish","votes":307,"clickcount":1,"codec":"AAC+","bitrate":48,"streams":[{"url":"https://23103.live.streamtheworld.com:443/XHPSFMAAC.aac","format":"aac+","bitrate":48,"reliability":1}],"state":"","languagecodes":"es"},{"id":"0ccb9e97-6635-4600-9f79-db591431dd78","name":"Like 105.7 FM","country":"PA","tags":[],"homepage":"https://like105.com/","favicon":"https://like105.com/wp-content/uploads/2024/05/Like-1057fm-Logo-2024-600x147.png","language":"","votes":13,"clickcount":1,"codec":"AAC+","bitrate":88,"streams":[{"url":"https://www.streaming507.net:8020/stream","format":"aac+","bitrate":88,"reliability":1}],"state":"","languagecodes":""},{"id":"1317c913-512c-48d1-bddc-be42e2e4b099","name":"AL TOPE RADIO","country":"PA","tags":[],"homepage":"https://www.altoperadio.com/","favicon":"https://cdn.onlineradiobox.com/img/l/2/33452.v5.png","language":"","votes":19,"clickcount":1,"codec":"MP3","bitrate":320,"streams":[{"url":"https://server.laradio.online/proxy/edwin_chacon?mp=/stream","format":"mp3","bitrate":320,"reliability":1}],"state":"","languagecodes":""},{"id":"cb57164d-ddb9-496a-8dcb-0ebd54c66b85","name":"Beat Life Panama","country":"PA","tags":["80s","90s","pop"],"homepage":"https://beatlifepanama.com/","favicon":"https://static2.mytuner.mobi/media/tvos_radios/MypDp5LTEv.png","language":"","votes":18,"clickcount":1,"codec":"AAC+","bitrate":64,"streams":[{"url":"https://cast4.asurahosting.com/proxy/ondabra2/stream","format":"aac+","bitrate":64,"reliability":1}],"state":"","languagecodes":"es-419"},{"id":"6c9cb2c9-55d2-4052-a415-7bfeaef44204","name":"KW Continente","country":"PA","tags":[],"homepage":"https://kwcontinente.com/","favicon":"https://kwcontinente.com/wp-content/uploads/2023/05/Logo-kW-e1682963097526.png","language":"","votes":12,"clickcount":1,"codec":"MP3","bitrate":64,"streams":[{"url":"https://s1.voscast.com:11355/stream.ogg","format":"mp3","bitrate":64,"reliability":1}],"state":"","languagecodes":""},{"id":"020af3ff-9191-49e5-b3de-854c32c1ca30","name":"LIKE 105 FM","country":"PA","tags":[],"homepage":"https://www.like105.com/","favicon":"","language":"","votes":87,"clickcount":0,"codec":"AAC+","bitrate":88,"streams":[{"url":"https://www.streaming507.net:8020/stream","format":"aac+","bitrate":88,"reliability":1}],"state":"","languagecodes":""}]
