[{"name":"Canal Motor","iptv_urls":["https://digicom.hls.iptvdc.com/canalmotor/index.m3u8","https://digicom.hls.iptvdc.com/motorstv/index.m3u8"],"youtube_urls":[],"language":"eng","country":"no","isGeoBlocked":false,"id":"CanalMotor.no","logo":"https://i.imgur.com/nCAt3QN.png"},{"name":"Frikanalen","iptv_urls":["https://frikanalen.no/stream/index.m3u8"],"youtube_urls":[],"language":"nor","country":"no","isGeoBlocked":false,"id":"Frikanalen.no","logo":"https://i.imgur.com/rY3Owxl.png"},{"name":"TV Østfold","iptv_urls":["https://streamnorge.com:8088/hls/tvo.m3u8"],"youtube_urls":[],"language":"nor","country":"no","isGeoBlocked":false,"id":"TVstfold.no","logo":null}]
